{"color":"#C61D23","headsign":"Alfragide (Hosp Veterinário)","id":"1001_0_2","long_name":"Alfragide (Estr Seminario) - Reboleira (Estação)","line_id":"1001","shape_id":"2_4X7ZR","path":[{"index":1,"name":"Reboleira (Estação) P3","id":"030844","lat":"38.750066","lon":"-9.221399","lines":["1001","1015"],"schedule":{"travel_time":0,"stop_id":"030844"}},{"index":2,"name":"Av Dom Carlos I (Aqueduto)","id":"030047","lat":"38.748849","lon":"-9.218426","lines":["1001","1015","1506","1704","1718"],"schedule":{"travel_time":1,"stop_id":"030047"}},{"index":3,"name":"Praça Águas Livres 2A","id":"030049","lat":"38.746875","lon":"-9.216116","lines":["1001","1015","1501","1507","1510","1704","1713","1718"],"schedule":{"travel_time":1,"stop_id":"030049"}},{"index":4,"name":"Av República 15B","id":"030040","lat":"38.745973","lon":"-9.212380","lines":["1001","1507","1704","1718"],"schedule":{"travel_time":1,"stop_id":"030040"}},{"index":5,"name":"Buraca (X) Cova Moura","id":"030051","lat":"38.743964","lon":"-9.211074","lines":["1001","1507","1704","1718"],"schedule":{"travel_time":0,"stop_id":"030051"}},{"index":6,"name":"Buraca (X) Cova Moura","id":"030052","lat":"38.744051","lon":"-9.210842","lines":["1001","1507","1704","1718"],"schedule":{"travel_time":1,"stop_id":"030052"}},{"index":7,"name":"R Trindade Coelho 19","id":"030038","lat":"38.744177","lon":"-9.210299","lines":["1001","1507","1704"],"schedule":{"travel_time":0,"stop_id":"030038"}},{"index":8,"name":"R Trindade Coelho (X) Pcta Conde Arnoso","id":"030053","lat":"38.744248","lon":"-9.208001","lines":["1001","1507","1704"],"schedule":{"travel_time":1,"stop_id":"030053"}},{"index":9,"name":"Estr Alfragide (CTT)","id":"030055","lat":"38.742752","lon":"-9.205946","lines":["1001","1507","1704"],"schedule":{"travel_time":1,"stop_id":"030055"}},{"index":10,"name":"R Luís Vaz de Camões (Centro Saúde)","id":"030032","lat":"38.740877","lon":"-9.208868","lines":["1001","1507","1704"],"schedule":{"travel_time":0,"stop_id":"030032"}},{"index":11,"name":"R 5 Outubro 18","id":"030030","lat":"38.742366","lon":"-9.211530","lines":["1001","1507","1704"],"schedule":{"travel_time":1,"stop_id":"030030"}},{"index":12,"name":"Av Republica (Pav Desportivo)","id":"030028","lat":"38.742386","lon":"-9.212775","lines":["1001","1507","1704","1718"],"schedule":{"travel_time":1,"stop_id":"030028"}},{"index":13,"name":"Alfragide (F Aérea)","id":"030026","lat":"38.738276","lon":"-9.214130","lines":["1001","1002","1507","1718"],"schedule":{"travel_time":1,"stop_id":"030026"}},{"index":14,"name":"Estr Alfragide (X) Praceta das Gaias","id":"030024","lat":"38.738231","lon":"-9.212534","lines":["1001","1704","1713","1718"],"schedule":{"travel_time":0,"stop_id":"030024"}},{"index":15,"name":"Bairro Zambujal 1","id":"030022","lat":"38.738680","lon":"-9.210333","lines":["1001"],"schedule":{"travel_time":1,"stop_id":"030022"}},{"index":16,"name":"R das Galegas 13","id":"030020","lat":"38.737752","lon":"-9.208432","lines":["1001"],"schedule":{"travel_time":0,"stop_id":"030020"}},{"index":17,"name":"R das Galegas","id":"030018","lat":"38.735971","lon":"-9.209461","lines":["1001"],"schedule":{"travel_time":1,"stop_id":"030018"}},{"index":18,"name":"R da Misericórdia","id":"030016","lat":"38.733961","lon":"-9.210669","lines":["1001"],"schedule":{"travel_time":2,"stop_id":"030016"}},{"index":19,"name":"Escola Luís Madureira","id":"030014","lat":"38.732842","lon":"-9.213521","lines":["1001"],"schedule":{"travel_time":0,"stop_id":"030014"}},{"index":20,"name":"Escola Almeida Garrett","id":"030012","lat":"38.733430","lon":"-9.215333","lines":["1001"],"schedule":{"travel_time":1,"stop_id":"030012"}},{"index":21,"name":"Estr Zambujal (Escolas)","id":"030010","lat":"38.732643","lon":"-9.216079","lines":["1001","1501"],"schedule":{"travel_time":0,"stop_id":"030010"}},{"index":22,"name":"Alfragide Sul","id":"030059","lat":"38.733302","lon":"-9.217084","lines":["1001","1501"],"schedule":{"travel_time":1,"stop_id":"030059"}},{"index":23,"name":"Av Ivens","id":"030061","lat":"38.733545","lon":"-9.219579","lines":["1001","1501"],"schedule":{"travel_time":0,"stop_id":"030061"}},{"index":24,"name":"Alfragide (Hosp Veterinário)","id":"030001","lat":"38.734441","lon":"-9.220576","lines":["1001","1002","1506","1507","1712"],"schedule":{"travel_time":1,"stop_id":"030001"}}]}