{"color":"#C61D23","headsign":"Montelavar (Largo)","id":"1634_0_1","long_name":"Fonte Da Aranha - Montelavar (Largo)","line_id":"1634","shape_id":"523_4X7ZR","path":[{"index":1,"name":"Fonte da Aranha","id":"172494","lat":"38.827169","lon":"-9.277724","lines":["1208","1235","1508","1634"],"schedule":{"travel_time":0,"stop_id":"172494"}},{"index":2,"name":"Estr Principal (X) R J Deus (Mancebas)","id":"170342","lat":"38.829830","lon":"-9.274824","lines":["1208","1235","1508","1634","1637"],"schedule":{"travel_time":1,"stop_id":"170342"}},{"index":3,"name":"Estr Principal 2","id":"170340","lat":"38.831414","lon":"-9.271566","lines":["1208","1235","1508","1634","1637"],"schedule":{"travel_time":1,"stop_id":"170340"}},{"index":4,"name":"Av José Mª Pais (X) Tv José Mª Pais","id":"170338","lat":"38.835180","lon":"-9.268718","lines":["1208","1235","1508","1634"],"schedule":{"travel_time":1,"stop_id":"170338"}},{"index":5,"name":"Av José Maria Pais (Acesso Aviário)","id":"170336","lat":"38.837912","lon":"-9.270806","lines":["1208","1235","1508","1634"],"schedule":{"travel_time":0,"stop_id":"170336"}},{"index":6,"name":"Av José Maria Pais 96 (Casal Vacaria)","id":"170334","lat":"38.839954","lon":"-9.272678","lines":["1208","1235","1508","1634"],"schedule":{"travel_time":1,"stop_id":"170334"}},{"index":7,"name":"Av D Afonso Henriques 31","id":"170332","lat":"38.842016","lon":"-9.273341","lines":["1208","1235","1508","1634"],"schedule":{"travel_time":1,"stop_id":"170332"}},{"index":8,"name":"R da Serra (X) R Amália Rodrigues","id":"170397","lat":"38.844116","lon":"-9.272710","lines":["1208","1235","1508","1634","1635"],"schedule":{"travel_time":0,"stop_id":"170397"}},{"index":9,"name":"R Serra 56","id":"170328","lat":"38.846589","lon":"-9.271159","lines":["1208","1235","1508","1634","1635"],"schedule":{"travel_time":1,"stop_id":"170328"}},{"index":10,"name":"R da Serra (Campo Futebol)","id":"170326","lat":"38.847753","lon":"-9.269100","lines":["1208","1235","1508","1634","1635"],"schedule":{"travel_time":0,"stop_id":"170326"}},{"index":11,"name":"Av Gen Humb Delgado 86","id":"172047","lat":"38.850201","lon":"-9.263932","lines":["1508","1634","1635"],"schedule":{"travel_time":1,"stop_id":"172047"}},{"index":12,"name":"Almargem Bispo (Centro saúde)","id":"171222","lat":"38.851318","lon":"-9.264497","lines":["1235","1508","1634","1635"],"schedule":{"travel_time":1,"stop_id":"171222"}},{"index":13,"name":"Av Gen Humb Delgado (X) Av Joaq Silva","id":"171220","lat":"38.848562","lon":"-9.262329","lines":["1235","1634","1635"],"schedule":{"travel_time":0,"stop_id":"171220"}},{"index":14,"name":"Av Joaquim Silva (X) Rapoula","id":"171218","lat":"38.849038","lon":"-9.260838","lines":["1235","1634","1635"],"schedule":{"travel_time":1,"stop_id":"171218"}},{"index":15,"name":"Av Joaquim Silva (Fonte Pedra)","id":"171216","lat":"38.850284","lon":"-9.258722","lines":["1235","1634","1635"],"schedule":{"travel_time":0,"stop_id":"171216"}},{"index":16,"name":"Albogas (X) Loures","id":"171214","lat":"38.853268","lon":"-9.257732","lines":["1235","1634","1635"],"schedule":{"travel_time":1,"stop_id":"171214"}},{"index":17,"name":"R Asp Rodrigo Feliciano Antunes 63","id":"171212","lat":"38.858180","lon":"-9.258514","lines":["1235","1634","1635","2620","2621","2785"],"schedule":{"travel_time":1,"stop_id":"171212"}},{"index":18,"name":"R a Rodr Felic Antun (X)R Visc Dasseca","id":"171210","lat":"38.861785","lon":"-9.251006","lines":["1235","1634","1635"],"schedule":{"travel_time":2,"stop_id":"171210"}},{"index":19,"name":"R Gen Barnabé António Ferreira 66","id":"172391","lat":"38.865191","lon":"-9.251292","lines":["1634","2620","2621","2785"],"schedule":{"travel_time":1,"stop_id":"172391"}},{"index":20,"name":"R Gen Barnabé António Ferreira 112","id":"172393","lat":"38.866681","lon":"-9.252527","lines":["1634","2620","2621","2785"],"schedule":{"travel_time":0,"stop_id":"172393"}},{"index":21,"name":"R Gen Barnabé António Ferreira 168","id":"172395","lat":"38.868588","lon":"-9.256131","lines":["1634"],"schedule":{"travel_time":1,"stop_id":"172395"}},{"index":22,"name":"R José Salvador (X) R Moínho","id":"080051","lat":"38.870780","lon":"-9.257647","lines":["1634"],"schedule":{"travel_time":1,"stop_id":"080051"}},{"index":23,"name":"R Sargento Francisco Pontes 3 (Igreja)","id":"172399","lat":"38.876393","lon":"-9.261738","lines":["1634"],"schedule":{"travel_time":1,"stop_id":"172399"}},{"index":24,"name":"R Gen Barn Ant Ferr 129","id":"172401","lat":"38.877070","lon":"-9.266876","lines":["1634"],"schedule":{"travel_time":1,"stop_id":"172401"}},{"index":25,"name":"R Gen ant Ferr Barnabé (Negrais park)","id":"172403","lat":"38.877478","lon":"-9.271335","lines":["1634"],"schedule":{"travel_time":1,"stop_id":"172403"}},{"index":26,"name":"R Gen Barn Ant Ferr (X) R Serrados","id":"172405","lat":"38.878329","lon":"-9.273643","lines":["1634"],"schedule":{"travel_time":0,"stop_id":"172405"}},{"index":27,"name":"Negrais (Soc Recreativa)","id":"171223","lat":"38.878770","lon":"-9.277727","lines":["1634"],"schedule":{"travel_time":1,"stop_id":"171223"}},{"index":28,"name":"R Gen Barnabé António Ferreira46","id":"172407","lat":"38.877292","lon":"-9.280744","lines":["1634"],"schedule":{"travel_time":1,"stop_id":"172407"}},{"index":29,"name":"Av Lapias (X) Alfouvar","id":"172409","lat":"38.870282","lon":"-9.286776","lines":["1634"],"schedule":{"travel_time":2,"stop_id":"172409"}},{"index":30,"name":"Av Lápias 519","id":"172414","lat":"38.866768","lon":"-9.298981","lines":["1634"],"schedule":{"travel_time":3,"stop_id":"172414"}},{"index":31,"name":"Av Lapias (X) R Liga a Pedra Furada","id":"171238","lat":"38.869274","lon":"-9.298091","lines":["1634"],"schedule":{"travel_time":0,"stop_id":"171238"}},{"index":32,"name":"Av Roma 62","id":"171241","lat":"38.872314","lon":"-9.301777","lines":["1240","1634"],"schedule":{"travel_time":1,"stop_id":"171241"}},{"index":33,"name":"Av Roma 98","id":"171243","lat":"38.875442","lon":"-9.304523","lines":["1240","1634"],"schedule":{"travel_time":1,"stop_id":"171243"}},{"index":34,"name":"Lgo de Anços (Chafariz)","id":"171245","lat":"38.877026","lon":"-9.306443","lines":["1240","1634"],"schedule":{"travel_time":1,"stop_id":"171245"}},{"index":35,"name":"Av Roma 98 (Lavadouro pub)","id":"171244","lat":"38.875283","lon":"-9.304446","lines":["1240","1634"],"schedule":{"travel_time":0,"stop_id":"171244"}},{"index":36,"name":"Av Roma 53","id":"171242","lat":"38.871976","lon":"-9.301449","lines":["1240","1634"],"schedule":{"travel_time":1,"stop_id":"171242"}},{"index":37,"name":"R Liga a Pedra Furada (X) Av Lapias","id":"171237","lat":"38.869125","lon":"-9.298088","lines":["1240","1634"],"schedule":{"travel_time":1,"stop_id":"171237"}},{"index":38,"name":"Av Lapias 538","id":"172413","lat":"38.866637","lon":"-9.299127","lines":["1634"],"schedule":{"travel_time":1,"stop_id":"172413"}},{"index":39,"name":"Av Lapias (Cabine Electrica)","id":"172415","lat":"38.864197","lon":"-9.300660","lines":["1634"],"schedule":{"travel_time":0,"stop_id":"172415"}},{"index":40,"name":"Av Lápias (Fonte Lage)","id":"172417","lat":"38.861882","lon":"-9.306889","lines":["1634"],"schedule":{"travel_time":2,"stop_id":"172417"}},{"index":41,"name":"R D António Granja (Serrões)","id":"172419","lat":"38.862129","lon":"-9.310393","lines":["1634"],"schedule":{"travel_time":0,"stop_id":"172419"}},{"index":42,"name":"Maceira 2 (Largo)","id":"171251","lat":"38.866275","lon":"-9.314334","lines":["1240","1634"],"schedule":{"travel_time":2,"stop_id":"171251"}},{"index":43,"name":"Largo 25 Abril 1","id":"171253","lat":"38.866441","lon":"-9.316284","lines":["1240","1634"],"schedule":{"travel_time":0,"stop_id":"171253"}},{"index":44,"name":"R Ant Silva e Castro 1 (Jd Plátanos)","id":"171255","lat":"38.865075","lon":"-9.318066","lines":["1240","1634"],"schedule":{"travel_time":1,"stop_id":"171255"}},{"index":45,"name":"R Ant Silva e Castro 1 (X) Av Lapias","id":"172421","lat":"38.861734","lon":"-9.319162","lines":["1634"],"schedule":{"travel_time":0,"stop_id":"172421"}},{"index":46,"name":"Av Lápias (Fte X) R Casal Ossos","id":"172559","lat":"38.860090","lon":"-9.322133","lines":["1634"],"schedule":{"travel_time":1,"stop_id":"172559"}},{"index":47,"name":"R 5 Outubro 24","id":"172423","lat":"38.858203","lon":"-9.325183","lines":["1255","1634"],"schedule":{"travel_time":1,"stop_id":"172423"}},{"index":48,"name":"Av da Liberdade Fte 113","id":"172099","lat":"38.858384","lon":"-9.326006","lines":["1512","1634"],"schedule":{"travel_time":0,"stop_id":"172099"}},{"index":49,"name":"Avenida Liberdade (Fte Supermercado)","id":"172561","lat":"38.861174","lon":"-9.326450","lines":["1512","1634"],"schedule":{"travel_time":1,"stop_id":"172561"}},{"index":50,"name":"R Vimal (Escola)","id":"171263","lat":"38.863413","lon":"-9.327526","lines":["1240","1255","1512","1634"],"schedule":{"travel_time":0,"stop_id":"171263"}},{"index":51,"name":"R Arqto José Luis Monteiro (Escola)","id":"171265","lat":"38.863262","lon":"-9.329079","lines":["1240","1255","1512","1634"],"schedule":{"travel_time":1,"stop_id":"171265"}},{"index":52,"name":"Montelavar (Largo)","id":"171267","lat":"38.860778","lon":"-9.332828","lines":["1240","1255","1512","1634","2626"],"schedule":{"travel_time":1,"stop_id":"171267"}}]}