{"color":"#C61D23","headsign":"Colégio Militar (Metro)","id":"1720_0_1","long_name":"Casal de Cambra - Colégio Militar (Metro) via Queluz-Belas (Estação)","line_id":"1720","path":[{"index":1,"name":"Casal Cambra (Centro saúde)","id":"171553","lines":["1244","1509","1515","1516","1517","1637","1709","1710","1719","1720","2702"],"schedule":{"travel_time":0,"stop_id":"171553"}},{"index":2,"name":"Av Lisboa 80","id":"171555","lines":["1244","1509","1515","1516","1517","1637","1709","1710","1719","1720","2702"],"schedule":{"travel_time":0,"stop_id":"171555"}},{"index":3,"name":"Av Brasil 42A","id":"172049","lines":["1509","1515","1720"],"schedule":{"travel_time":1,"stop_id":"172049"}},{"index":4,"name":"Av Brasil 68 (Fte Jardim Infância)","id":"172051","lines":["1509","1515","1720"],"schedule":{"travel_time":0,"stop_id":"172051"}},{"index":5,"name":"Av Moçambique (Parq Casal Cambra)","id":"172053","lines":["1509","1515","1517","1711","1720"],"schedule":{"travel_time":1,"stop_id":"172053"}},{"index":6,"name":"Casal Cambra (Escola)","id":"171550","lines":["1244","1509","1515","1516","1517","1720"],"schedule":{"travel_time":1,"stop_id":"171550"}},{"index":7,"name":"R Lyon 4A","id":"172127","lines":["1515","1517","1720"],"schedule":{"travel_time":1,"stop_id":"172127"}},{"index":8,"name":"R Castelhana 55 (X) R J Augusto Costa","id":"030642","lines":["1509","1515","1720"],"schedule":{"travel_time":1,"stop_id":"030642"}},{"index":9,"name":"A-da-Beja (Fonte Sta)","id":"030643","lines":["1509","1515","1720"],"schedule":{"travel_time":1,"stop_id":"030643"}},{"index":10,"name":"R Fernando Maia 27","id":"030710","lines":["1509","1515","1517","1720"],"schedule":{"travel_time":1,"stop_id":"030710"}},{"index":11,"name":"R Fernando Maia (X) R Campos","id":"030708","lines":["1509","1515","1517","1720"],"schedule":{"travel_time":0,"stop_id":"030708"}},{"index":12,"name":"R Fernando Maia (Viveiros R Bacará)","id":"030713","lines":["1515","1720"],"schedule":{"travel_time":2,"stop_id":"030713"}},{"index":13,"name":"R Fernando Maia (Fte ETAR)","id":"030878","lines":["1515","1720"],"schedule":{"travel_time":1,"stop_id":"030878"}},{"index":14,"name":"EN 250 (X) Estrada Águas Livres","id":"030593","lines":["1508","1515","1516","1603","1720","2605"],"schedule":{"travel_time":1,"stop_id":"030593"}},{"index":15,"name":"Estr Águas Livres (Esc S Silveira)","id":"030595","lines":["1508","1515","1603","1720"],"schedule":{"travel_time":3,"stop_id":"030595"}},{"index":16,"name":"Estr Ág Livres 155 (Cas S Vicente)","id":"030597","lines":["1508","1515","1603","1720"],"schedule":{"travel_time":1,"stop_id":"030597"}},{"index":17,"name":"Carenque (Lgo)","id":"030599","lines":["1508","1515","1519","1603","1720"],"schedule":{"travel_time":1,"stop_id":"030599"}},{"index":18,"name":"Estr Carenque 21d","id":"172037","lines":["1508","1515","1519","1603","1720"],"schedule":{"travel_time":2,"stop_id":"172037"}},{"index":19,"name":"Carenque (X) Bica Costa","id":"172039","lines":["1508","1515","1519","1603","1720"],"schedule":{"travel_time":1,"stop_id":"172039"}},{"index":20,"name":"R Bica Costa 31","id":"172079","lines":["1512","1515","1718","1720"],"schedule":{"travel_time":1,"stop_id":"172079"}},{"index":21,"name":"Pendão (Bica Costa)","id":"171051","lines":["1230","1512","1513","1515","1718","1720"],"schedule":{"travel_time":1,"stop_id":"171051"}},{"index":22,"name":"Av Mig Bombarda (Pcta M Av Humb Cruz)","id":"170595","lines":["1212","1224","1226","1513","1515","1716","1718","1720"],"schedule":{"travel_time":1,"stop_id":"170595"}},{"index":23,"name":"Av Miguel Bombarda 91","id":"170597","lines":["1212","1224","1226","1513","1515","1716","1718","1720"],"schedule":{"travel_time":0,"stop_id":"170597"}},{"index":24,"name":"Queluz - Belas (Estação)","id":"170599","lines":["1224","1513","1515","1716","1718","1720"],"schedule":{"travel_time":1,"stop_id":"170599"}},{"index":25,"name":"Av Elias Garcia 219","id":"170925","lines":["1230","1512","1515","1518","1530","1601","1715","1716","1720","1721"],"schedule":{"travel_time":3,"stop_id":"170925"}},{"index":26,"name":"Queluz (4 Caminhos)","id":"172499","lines":["1515","1518","1530","1601","1715","1717","1720","1721"],"schedule":{"travel_time":1,"stop_id":"172499"}},{"index":27,"name":"Av Elias Garcia 25","id":"171027","lines":["1230","1509","1510","1512","1514","1515","1518","1519","1601","1716","1717","1720","1721"],"schedule":{"travel_time":2,"stop_id":"171027"}},{"index":28,"name":"R Elias Garcia (Escolas)","id":"030328","lines":["1009","1014","1508","1509","1510","1514","1515","1518","1601","1603","1716","1717","1718","1720","1721"],"schedule":{"travel_time":1,"stop_id":"030328"}},{"index":29,"name":"R Elias Garcia 323","id":"030326","lines":["1009","1014","1508","1509","1510","1514","1515","1518","1601","1716","1717","1718","1720","1721"],"schedule":{"travel_time":1,"stop_id":"030326"}},{"index":30,"name":"Amadora (Hosp Luz)","id":"030322","lines":["1014","1508","1510","1515","1601","1716","1718","1720","1721"],"schedule":{"travel_time":1,"stop_id":"030322"}},{"index":31,"name":"R Elias Garcia 362","id":"030475","lines":["1009","1014","1508","1509","1510","1514","1515","1601","1716","1718","1720","1721"],"schedule":{"travel_time":1,"stop_id":"030475"}},{"index":32,"name":"R Luís Camões 9 (CTT)","id":"030477","lines":["1002","1009","1014","1501","1502","1508","1509","1510","1514","1515","1601","1712","1714","1716","1718","1720","1721"],"schedule":{"travel_time":1,"stop_id":"030477"}},{"index":33,"name":"Estr Salv Allende (Posto Combustivel)","id":"030601","lines":["1002","1508","1514","1515","1601","1712","1720","1721"],"schedule":{"travel_time":1,"stop_id":"030601"}},{"index":34,"name":"Praceta Miguel Cláudio 2","id":"030603","lines":["1002","1508","1514","1515","1601","1712","1720","1721"],"schedule":{"travel_time":1,"stop_id":"030603"}},{"index":35,"name":"R Elias Garcia 103","id":"030605","lines":["1508","1514","1515","1518","1601","1707","1717","1720","1721"],"schedule":{"travel_time":1,"stop_id":"030605"}},{"index":36,"name":"R Elias Garcia 88","id":"030607","lines":["1508","1514","1515","1518","1601","1707","1717","1720","1721"],"schedule":{"travel_time":1,"stop_id":"030607"}},{"index":37,"name":"R Elias Garcia 43","id":"030609","lines":["1508","1515","1601","1707","1717","1720","1721"],"schedule":{"travel_time":1,"stop_id":"030609"}},{"index":38,"name":"R Elias Garcia 23I","id":"030860","lines":["1508","1515","1601","1707","1717","1720","1721"],"schedule":{"travel_time":0,"stop_id":"030860"}},{"index":39,"name":"Amadora Este (Metro) P1","id":"030853","lines":["1707","1717","1720","1721"],"schedule":{"travel_time":2,"stop_id":"030853"}},{"index":40,"name":"R Elias Garcia (Hipermercado)","id":"030797","lines":["1707","1717","1720","1721"],"schedule":{"travel_time":2,"stop_id":"030797"}},{"index":41,"name":"R Elias Garcia 15","id":"030302","lines":["1707","1717","1720","1721"],"schedule":{"travel_time":1,"stop_id":"030302"}},{"index":42,"name":"R Elias Garcia (Portas de Benfica)","id":"030300","lines":["1707","1713","1717","1720","1721"],"schedule":{"travel_time":1,"stop_id":"030300"}},{"index":43,"name":"Estr Benfica (Mercado)","id":"060044","lines":["1707","1717","1720","1721"],"schedule":{"travel_time":1,"stop_id":"060044"}},{"index":44,"name":"Igreja Benfica","id":"060051","lines":["1707","1717","1720","1721"],"schedule":{"travel_time":2,"stop_id":"060051"}},{"index":45,"name":"Esc Pedro Santarém","id":"060053","lines":["1707","1717","1720","1721"],"schedule":{"travel_time":1,"stop_id":"060053"}},{"index":46,"name":"Calhariz","id":"060055","lines":["1707","1717","1720","1721"],"schedule":{"travel_time":1,"stop_id":"060055"}},{"index":47,"name":"Colégio Militar (Metro) P11","id":"060131","lines":["1720"],"schedule":{"travel_time":2,"stop_id":"060131"}}]}